win_aliases/__init__.py
win_bash_aliases-0.0.3.dist-info/LICENSE
win_bash_aliases-0.0.3.dist-info/METADATA
win_bash_aliases-0.0.3.dist-info/WHEEL
win_bash_aliases-0.0.3.dist-info/entry_points.txt
win_bash_aliases-0.0.3.dist-info/top_level.txt
win_bash_aliases-0.0.3.dist-info/RECORD
